fusion123/__init__.py
fusion123/converter.py
fusion123-0.1.0.data/scripts/123fusion
fusion123-0.1.0.data/scripts/123fusion.py
fusion123-0.1.0.data/scripts/fusion123
src/__init__.py
src/converter.py
fusion123-0.1.0.dist-info/LICENSE
fusion123-0.1.0.dist-info/METADATA
fusion123-0.1.0.dist-info/WHEEL
fusion123-0.1.0.dist-info/top_level.txt
fusion123-0.1.0.dist-info/RECORD
