Metadata-Version: 2.1
Name: fusion123
Version: 0.1.0
Summary: Converts 123D design CAD files into Fusion 360 CAD files
Home-page: https://github.com/bennymeg/123-Fusion
Author: Benny Megidish
Author-email: bennymegk@gmail.com
License: UNKNOWN
Platform: UNKNOWN
Classifier: Programming Language :: Python :: 3
Classifier: License :: OSI Approved :: MIT License
Classifier: Operating System :: OS Independent
